census_map_consolidator/__init__.py
census_map_consolidator-0.0.6.dist-info/LICENSE
census_map_consolidator-0.0.6.dist-info/METADATA
census_map_consolidator-0.0.6.dist-info/WHEEL
census_map_consolidator-0.0.6.dist-info/top_level.txt
census_map_consolidator-0.0.6.dist-info/RECORD
